[
  {
    "id": "482c1ac5-ab0f-4f0e-b76c-4ab7a4ac14ae",
    "code": "AJVA45BQ",
    "audioUrl": "http://localhost:3000/api/audio/stream/9f3b2880-36fd-41e0-91f7-7c4cae13b5ba.mp3",
    "audioFilename": "processed/9f3b2880-36fd-41e0-91f7-7c4cae13b5ba.mp3",
    "title": "De Shate para Loops",
    "description": "holiii te quero mucho",
    "createdAt": "2026-01-24T22:46:55.941Z",
    "pageUrl": "http://localhost:3000/page/AJVA45BQ",
    "isPersonalized": true,
    "senderName": "Shate",
    "recipientName": "Loops",
    "writtenMessage": "holiii te quero mucho",
    "imageUrl": "http://localhost:3000/api/images/6060c98e-476c-430c-b15b-1b36cd51a9c3.png",
    "imageFilename": "6060c98e-476c-430c-b15b-1b36cd51a9c3.png",
    "personalizedAt": "2026-01-26T20:09:54.052Z",
    "playCount": 2
  },
  {
    "id": "5f3e4be8-0d05-40d2-81db-75c6fc9699b1",
    "code": "R3CCGG4T",
    "audioUrl": "http://localhost:3000/api/audio/stream/dummy-audio.mp3",
    "audioFilename": "dummy-audio.mp3",
    "title": "Tarjeta 1",
    "description": "Página de prueba 1 - Lista para personalizar",
    "createdAt": "2026-01-24T22:53:31.269Z",
    "pageUrl": "http://localhost:3000/page/R3CCGG4T",
    "isPersonalized": false,
    "playCount": 0,
    "maxPlays": 5,
    "expirationDate": "2026-02-14T06:00:00.000Z"
  },
  {
    "id": "0054fb5e-cb67-4a8b-9dd4-961834c15cc9",
    "code": "TPBCVD98",
    "audioUrl": "http://localhost:3000/api/audio/stream/dummy-audio.mp3",
    "audioFilename": "dummy-audio.mp3",
    "title": "Tarjeta 2",
    "description": "Página de prueba 2 - Lista para personalizar",
    "createdAt": "2026-01-24T22:53:31.272Z",
    "pageUrl": "http://localhost:3000/page/TPBCVD98",
    "isPersonalized": false,
    "playCount": 0,
    "maxPlays": 5,
    "expirationDate": "2026-02-14T06:00:00.000Z"
  },
  {
    "id": "b97673cf-b643-44f8-bbc6-a1b658f2132d",
    "code": "J439WEEM",
    "audioUrl": "http://localhost:3000/api/audio/stream/dummy-audio.mp3",
    "audioFilename": "dummy-audio.mp3",
    "title": "Tarjeta 3",
    "description": "Página de prueba 3 - Lista para personalizar",
    "createdAt": "2026-01-24T22:53:31.274Z",
    "pageUrl": "http://localhost:3000/page/J439WEEM",
    "isPersonalized": false,
    "playCount": 0,
    "maxPlays": 5,
    "expirationDate": "2026-02-14T06:00:00.000Z"
  },
  {
    "id": "5dfc277c-d744-47e7-b929-e3fb975e6463",
    "code": "YVLUVKWC",
    "audioUrl": "http://localhost:3000/api/audio/stream/dummy-audio.mp3",
    "audioFilename": "dummy-audio.mp3",
    "title": "Tarjeta 4",
    "description": "Página de prueba 4 - Lista para personalizar",
    "createdAt": "2026-01-24T22:53:31.278Z",
    "pageUrl": "http://localhost:3000/page/YVLUVKWC",
    "isPersonalized": false,
    "playCount": 0,
    "maxPlays": 5,
    "expirationDate": "2026-02-14T06:00:00.000Z"
  },
  {
    "id": "44dcb885-07d6-4320-9e31-76c1b0efa677",
    "code": "4R8NWRB2",
    "audioUrl": "http://localhost:3000/api/audio/stream/dummy-audio.mp3",
    "audioFilename": "dummy-audio.mp3",
    "title": "Tarjeta 5",
    "description": "Página de prueba 5 - Lista para personalizar",
    "createdAt": "2026-01-24T22:53:31.282Z",
    "pageUrl": "http://localhost:3000/page/4R8NWRB2",
    "isPersonalized": false,
    "playCount": 0,
    "maxPlays": 5,
    "expirationDate": "2026-02-14T06:00:00.000Z"
  },
  {
    "id": "895d8c16-9b6a-4fa0-bf95-f79930fb8cad",
    "code": "A4M5NAJX",
    "audioUrl": "http://localhost:3000/api/audio/stream/dummy-audio.mp3",
    "audioFilename": "dummy-audio.mp3",
    "title": "Tarjeta 6",
    "description": "Página de prueba 6 - Lista para personalizar",
    "createdAt": "2026-01-24T22:53:31.286Z",
    "pageUrl": "http://localhost:3000/page/A4M5NAJX",
    "isPersonalized": false,
    "playCount": 0,
    "maxPlays": 5,
    "expirationDate": "2026-02-14T06:00:00.000Z"
  },
  {
    "id": "358f3f5f-22aa-4c37-ad3d-5a2803228cc0",
    "code": "C4763W3K",
    "audioUrl": "http://localhost:3000/api/audio/stream/dummy-audio.mp3",
    "audioFilename": "dummy-audio.mp3",
    "title": "Tarjeta 7",
    "description": "Página de prueba 7 - Lista para personalizar",
    "createdAt": "2026-01-24T22:53:31.289Z",
    "pageUrl": "http://localhost:3000/page/C4763W3K",
    "isPersonalized": false,
    "playCount": 0,
    "maxPlays": 5,
    "expirationDate": "2026-02-14T06:00:00.000Z"
  },
  {
    "id": "358c99b0-31be-4031-b860-63868cdcf13e",
    "code": "7SHAHPUZ",
    "audioUrl": "http://localhost:3000/api/audio/stream/dummy-audio.mp3",
    "audioFilename": "dummy-audio.mp3",
    "title": "Tarjeta 8",
    "description": "Página de prueba 8 - Lista para personalizar",
    "createdAt": "2026-01-24T22:53:31.293Z",
    "pageUrl": "http://localhost:3000/page/7SHAHPUZ",
    "isPersonalized": false,
    "playCount": 0,
    "maxPlays": 5,
    "expirationDate": "2026-02-14T06:00:00.000Z"
  },
  {
    "id": "f0a7734b-2ff4-4ce9-957c-2e380d24b34d",
    "code": "CXYBJXVM",
    "audioUrl": "http://localhost:3000/api/audio/stream/dummy-audio.mp3",
    "audioFilename": "dummy-audio.mp3",
    "title": "Tarjeta 9",
    "description": "Página de prueba 9 - Lista para personalizar",
    "createdAt": "2026-01-24T22:53:31.296Z",
    "pageUrl": "http://localhost:3000/page/CXYBJXVM",
    "isPersonalized": false,
    "playCount": 0,
    "maxPlays": 5,
    "expirationDate": "2026-02-14T06:00:00.000Z"
  },
  {
    "id": "d366ac9d-33f4-4cd1-bac5-833f1def29df",
    "code": "3PJ3743K",
    "audioUrl": "http://localhost:3000/api/audio/stream/948f9fef-5e35-4fc9-b3d4-2f1d00a2abe1.mp3",
    "audioFilename": "processed/948f9fef-5e35-4fc9-b3d4-2f1d00a2abe1.mp3",
    "title": "De Shate para Pha",
    "description": "besssooo❤️",
    "createdAt": "2026-01-24T22:53:31.299Z",
    "pageUrl": "http://localhost:3000/page/3PJ3743K",
    "isPersonalized": true,
    "playCount": 5,
    "maxPlays": 5,
    "expirationDate": "2026-02-14T06:00:00.000Z",
    "senderName": "Shate",
    "recipientName": "Pha",
    "writtenMessage": "besssooo❤️",
    "personalizedAt": "2026-01-24T23:19:16.518Z"
  },
  {
    "id": "44ef6e3e-2f2b-401e-ac65-71282e130860",
    "code": "HKHJSXVN",
    "audioUrl": "http://localhost:3000/api/audio/stream/placeholder.mp3",
    "audioFilename": "placeholder.mp3",
    "title": "Starbucks - 123 - Tarjeta 1",
    "description": "Tarjeta 1 de 10 para Starbucks",
    "createdAt": "2026-01-26T20:16:09.711Z",
    "pageUrl": "http://localhost:3000/page/HKHJSXVN",
    "isPersonalized": false,
    "playCount": 0,
    "maxPlays": 5,
    "expirationDate": "2026-02-14T06:00:00.000Z"
  },
  {
    "id": "a8e5b1b0-df6d-4366-8da0-c2dd415aa4c3",
    "code": "UDEGE9UP",
    "audioUrl": "http://localhost:3000/api/audio/stream/placeholder.mp3",
    "audioFilename": "placeholder.mp3",
    "title": "Starbucks - 123 - Tarjeta 2",
    "description": "Tarjeta 2 de 10 para Starbucks",
    "createdAt": "2026-01-26T20:16:09.712Z",
    "pageUrl": "http://localhost:3000/page/UDEGE9UP",
    "isPersonalized": false,
    "playCount": 0,
    "maxPlays": 5,
    "expirationDate": "2026-02-14T06:00:00.000Z"
  },
  {
    "id": "2a02042e-6bf5-40ab-9f1b-bd4557e30799",
    "code": "GNGE5VPF",
    "audioUrl": "http://localhost:3000/api/audio/stream/placeholder.mp3",
    "audioFilename": "placeholder.mp3",
    "title": "Starbucks - 123 - Tarjeta 3",
    "description": "Tarjeta 3 de 10 para Starbucks",
    "createdAt": "2026-01-26T20:16:09.713Z",
    "pageUrl": "http://localhost:3000/page/GNGE5VPF",
    "isPersonalized": false,
    "playCount": 0,
    "maxPlays": 5,
    "expirationDate": "2026-02-14T06:00:00.000Z"
  },
  {
    "id": "4d79e3f4-7b98-4d98-9873-94abbd49006a",
    "code": "MGXDSNVE",
    "audioUrl": "http://localhost:3000/api/audio/stream/placeholder.mp3",
    "audioFilename": "placeholder.mp3",
    "title": "Starbucks - 123 - Tarjeta 4",
    "description": "Tarjeta 4 de 10 para Starbucks",
    "createdAt": "2026-01-26T20:16:09.714Z",
    "pageUrl": "http://localhost:3000/page/MGXDSNVE",
    "isPersonalized": false,
    "playCount": 0,
    "maxPlays": 5,
    "expirationDate": "2026-02-14T06:00:00.000Z"
  },
  {
    "id": "bec98ab0-d475-4cba-9cab-d5d751cd35d0",
    "code": "AD966N2R",
    "audioUrl": "http://localhost:3000/api/audio/stream/placeholder.mp3",
    "audioFilename": "placeholder.mp3",
    "title": "Starbucks - 123 - Tarjeta 5",
    "description": "Tarjeta 5 de 10 para Starbucks",
    "createdAt": "2026-01-26T20:16:09.714Z",
    "pageUrl": "http://localhost:3000/page/AD966N2R",
    "isPersonalized": false,
    "playCount": 0,
    "maxPlays": 5,
    "expirationDate": "2026-02-14T06:00:00.000Z"
  },
  {
    "id": "27334424-08fe-4940-94ef-8eea888b4e53",
    "code": "B2JF6E7P",
    "audioUrl": "http://localhost:3000/api/audio/stream/placeholder.mp3",
    "audioFilename": "placeholder.mp3",
    "title": "Starbucks - 123 - Tarjeta 6",
    "description": "Tarjeta 6 de 10 para Starbucks",
    "createdAt": "2026-01-26T20:16:09.715Z",
    "pageUrl": "http://localhost:3000/page/B2JF6E7P",
    "isPersonalized": false,
    "playCount": 0,
    "maxPlays": 5,
    "expirationDate": "2026-02-14T06:00:00.000Z"
  },
  {
    "id": "ebb3cd0b-9dc1-425a-b592-b4d013830614",
    "code": "S6FCCFTK",
    "audioUrl": "http://localhost:3000/api/audio/stream/placeholder.mp3",
    "audioFilename": "placeholder.mp3",
    "title": "Starbucks - 123 - Tarjeta 7",
    "description": "Tarjeta 7 de 10 para Starbucks",
    "createdAt": "2026-01-26T20:16:09.715Z",
    "pageUrl": "http://localhost:3000/page/S6FCCFTK",
    "isPersonalized": false,
    "playCount": 0,
    "maxPlays": 5,
    "expirationDate": "2026-02-14T06:00:00.000Z"
  },
  {
    "id": "4bf6d21a-430e-40e5-8124-ab2b8755a756",
    "code": "GFGKQ3RA",
    "audioUrl": "http://localhost:3000/api/audio/stream/placeholder.mp3",
    "audioFilename": "placeholder.mp3",
    "title": "Starbucks - 123 - Tarjeta 8",
    "description": "Tarjeta 8 de 10 para Starbucks",
    "createdAt": "2026-01-26T20:16:09.716Z",
    "pageUrl": "http://localhost:3000/page/GFGKQ3RA",
    "isPersonalized": false,
    "playCount": 0,
    "maxPlays": 5,
    "expirationDate": "2026-02-14T06:00:00.000Z"
  },
  {
    "id": "97eb40b7-74bf-423c-b80d-817402a7b455",
    "code": "E7DMSTH2",
    "audioUrl": "http://localhost:3000/api/audio/stream/placeholder.mp3",
    "audioFilename": "placeholder.mp3",
    "title": "Starbucks - 123 - Tarjeta 9",
    "description": "Tarjeta 9 de 10 para Starbucks",
    "createdAt": "2026-01-26T20:16:09.717Z",
    "pageUrl": "http://localhost:3000/page/E7DMSTH2",
    "isPersonalized": false,
    "playCount": 0,
    "maxPlays": 5,
    "expirationDate": "2026-02-14T06:00:00.000Z"
  },
  {
    "id": "98440975-19b4-445f-8ebb-bce320d51a24",
    "code": "U2ZE4KSV",
    "audioUrl": "http://localhost:3000/api/audio/stream/placeholder.mp3",
    "audioFilename": "placeholder.mp3",
    "title": "Starbucks - 123 - Tarjeta 10",
    "description": "Tarjeta 10 de 10 para Starbucks",
    "createdAt": "2026-01-26T20:16:09.719Z",
    "pageUrl": "http://localhost:3000/page/U2ZE4KSV",
    "isPersonalized": false,
    "playCount": 0,
    "maxPlays": 5,
    "expirationDate": "2026-02-14T06:00:00.000Z"
  }
]